setup_project/__init__.py
setup_project/create_project.py
setup_project/main.py
setup_project-0.1.0.dist-info/METADATA
setup_project-0.1.0.dist-info/WHEEL
setup_project-0.1.0.dist-info/entry_points.txt
setup_project-0.1.0.dist-info/top_level.txt
setup_project-0.1.0.dist-info/RECORD
